kerify
