Metadata-Version: 2.1
Name: kerify
Version: 0.0.2
Summary: Kerify
Home-page: https://github.com/WebOfTrust/kerify
Author: Philip S. Feairheller
Author-email: phil@healthkeri.com
License: Apache Software License 2.0
Project-URL: Documentation, https://kerify.readthedocs.io/
Project-URL: Changelog, https://kerify.readthedocs.io/en/latest/changelog.html
Project-URL: Issue Tracker, https://github.com/WebOfTrust/kerify/issues
Classifier: Development Status :: 3 - Alpha
Classifier: Intended Audience :: Developers
Classifier: License :: OSI Approved :: Apache Software License
Classifier: Operating System :: Unix
Classifier: Operating System :: POSIX
Classifier: Operating System :: Microsoft :: Windows
Classifier: Programming Language :: Python :: 3.10
Classifier: Programming Language :: Python :: Implementation :: CPython
Classifier: Topic :: Utilities
Requires-Python: >=3.12.2
License-File: LICENSE
Requires-Dist: keri>=1.2.0-dev0
Requires-Dist: multicommand>=1.0.0
Requires-Dist: http_sfv>=0.9.8
Requires-Dist: msgpack>=1.0.4
Requires-Dist: cbor2>=5.4.3
